kwcoco_dataloader/__init__.py
kwcoco_dataloader/exceptions.py
kwcoco_dataloader/heuristics.py
kwcoco_dataloader/cli/__init__.py
kwcoco_dataloader/cli/build_webdataset.py
kwcoco_dataloader/cli/special/__init__.py
kwcoco_dataloader/cli/special/finish_install.py
kwcoco_dataloader/demo/__init__.py
kwcoco_dataloader/demo/smart_kwcoco_demodata.py
kwcoco_dataloader/tasks/__init__.py
kwcoco_dataloader/tasks/fusion/__init__.py
kwcoco_dataloader/tasks/fusion/datamodules/__init__.py
kwcoco_dataloader/tasks/fusion/datamodules/balanced_sampling.py
kwcoco_dataloader/tasks/fusion/datamodules/batch_visualization.py
kwcoco_dataloader/tasks/fusion/datamodules/data_augment.py
kwcoco_dataloader/tasks/fusion/datamodules/data_utils.py
kwcoco_dataloader/tasks/fusion/datamodules/dynamic_channel_handler.py
kwcoco_dataloader/tasks/fusion/datamodules/kwcoco_datamodule.py
kwcoco_dataloader/tasks/fusion/datamodules/kwcoco_dataset.py
kwcoco_dataloader/tasks/fusion/datamodules/network_io.py
kwcoco_dataloader/tasks/fusion/datamodules/qa_bands.py
kwcoco_dataloader/tasks/fusion/datamodules/robust_normalizer.py
kwcoco_dataloader/tasks/fusion/datamodules/smart_mixins.py
kwcoco_dataloader/tasks/fusion/datamodules/spacetime_grid_builder.py
kwcoco_dataloader/tasks/fusion/datamodules/util_positional_encoding.py
kwcoco_dataloader/tasks/fusion/datamodules/temporal_sampling/__init__.py
kwcoco_dataloader/tasks/fusion/datamodules/temporal_sampling/affinity.py
kwcoco_dataloader/tasks/fusion/datamodules/temporal_sampling/exceptions.py
kwcoco_dataloader/tasks/fusion/datamodules/temporal_sampling/plots.py
kwcoco_dataloader/tasks/fusion/datamodules/temporal_sampling/sampler.py
kwcoco_dataloader/tasks/fusion/datamodules/temporal_sampling/time_kernel.py
kwcoco_dataloader/tasks/fusion/datamodules/temporal_sampling/time_kernel_grammar.py
kwcoco_dataloader/tasks/fusion/datamodules/temporal_sampling/utils.py
kwcoco_dataloader/utils/__init__.py
kwcoco_dataloader/utils/kwcoco_extensions.py
kwcoco_dataloader-0.1.2.dist-info/METADATA
kwcoco_dataloader-0.1.2.dist-info/WHEEL
kwcoco_dataloader-0.1.2.dist-info/top_level.txt
kwcoco_dataloader-0.1.2.dist-info/RECORD
